[
  {
    "mobId": 6130101,
    "mobName": "Mushmom",
    "itemId": 0,
    "itemName": "Meso",
    "chance": 0.4,
    "minQty": 800,
    "maxQty": 1196,
    "chineseItemName": "楓幣",
    "chineseMobName": "蘑菇王"
  },
  {
    "mobId": 6130101,
    "mobName": "Mushmom",
    "itemId": 2041045,
    "itemName": "Scroll for Cape for Defense 15%",
    "chance": 0.01,
    "minQty": 1,
    "maxQty": 4,
    "chineseItemName": "披風防禦卷軸15%",
    "chineseMobName": "蘑菇王"
  },
  {
    "mobId": 6130101,
    "mobName": "Mushmom",
    "itemId": 1032013,
    "itemName": "Red-Hearted Earrings",
    "chance": 0.04,
    "minQty": 1,
    "maxQty": 1,
    "chineseItemName": "愛心耳環",
    "chineseMobName": "蘑菇王"
  },
  {
    "mobId": 6130101,
    "mobName": "Mushmom",
    "itemId": 1032019,
    "itemName": "Crystal Flower Earrings",
    "chance": 0.01,
    "minQty": 1,
    "maxQty": 1,
    "chineseItemName": "水仙耳環",
    "chineseMobName": "蘑菇王"
  },
  {
    "mobId": 6130101,
    "mobName": "Mushmom",
    "itemId": 1092012,
    "itemName": "Steel Tower Shield",
    "chance": 0.007,
    "minQty": 1,
    "maxQty": 1,
    "chineseItemName": "鋼鐵方盾",
    "chineseMobName": "蘑菇王"
  },
  {
    "mobId": 6130101,
    "mobName": "Mushmom",
    "itemId": 1202004,
    "itemName": "Blaze Capsule",
    "chance": 0.005,
    "minQty": 1,
    "maxQty": 1,
    "chineseItemName": "火焰膠囊",
    "chineseMobName": "蘑菇王"
  },
  {
    "mobId": 6130101,
    "mobName": "Mushmom",
    "itemId": 1203012,
    "itemName": "Ilbi Throwing-Stars",
    "chance": 0.002,
    "minQty": 1,
    "maxQty": 1,
    "chineseItemName": "日之標",
    "chineseMobName": "蘑菇王"
  },
  {
    "mobId": 6130101,
    "mobName": "Mushmom",
    "itemId": 1372000,
    "itemName": "Fairy Wand",
    "chance": 0.04,
    "minQty": 1,
    "maxQty": 1,
    "chineseItemName": "妖精短杖",
    "chineseMobName": "蘑菇王"
  },
  {
    "mobId": 6130101,
    "mobName": "Mushmom",
    "itemId": 1382006,
    "itemName": "Thorns",
    "chance": 0.007,
    "minQty": 1,
    "maxQty": 1,
    "chineseItemName": "白龍之杖",
    "chineseMobName": "蘑菇王"
  },
  {
    "mobId": 6130101,
    "mobName": "Mushmom",
    "itemId": 2040001,
    "itemName": "Scroll for Helmet for Defense 60%",
    "chance": 0.003,
    "minQty": 1,
    "maxQty": 1,
    "chineseItemName": "頭盔防禦卷軸60%",
    "chineseMobName": "蘑菇王"
  },
  {
    "mobId": 6130101,
    "mobName": "Mushmom",
    "itemId": 2040024,
    "itemName": "Scroll for Helmet for INT 100%",
    "chance": 0.003,
    "minQty": 1,
    "maxQty": 1,
    "chineseItemName": "頭盔智力卷軸100%",
    "chineseMobName": "蘑菇王"
  },
  {
    "mobId": 6130101,
    "mobName": "Mushmom",
    "itemId": 2040301,
    "itemName": "Scroll for Earring for INT 60%",
    "chance": 0.003,
    "minQty": 1,
    "maxQty": 1,
    "chineseItemName": "耳環智力卷軸60%",
    "chineseMobName": "蘑菇王"
  },
  {
    "mobId": 6130101,
    "mobName": "Mushmom",
    "itemId": 2040401,
    "itemName": "Scroll for Topwear for Defense 60%",
    "chance": 0.003,
    "minQty": 1,
    "maxQty": 1,
    "chineseItemName": "上衣防禦卷軸60%",
    "chineseMobName": "蘑菇王"
  },
  {
    "mobId": 6130101,
    "mobName": "Mushmom",
    "itemId": 2040412,
    "itemName": "Scroll for Topwear for LUK 10%",
    "chance": 0.003,
    "minQty": 1,
    "maxQty": 1,
    "chineseItemName": "上衣幸運卷軸10%",
    "chineseMobName": "蘑菇王"
  },
  {
    "mobId": 6130101,
    "mobName": "Mushmom",
    "itemId": 2040501,
    "itemName": "Scroll for Overall Armor for DEX 60%",
    "chance": 0.003,
    "minQty": 1,
    "maxQty": 1,
    "chineseItemName": "套服敏捷卷軸60%",
    "chineseMobName": "蘑菇王"
  },
  {
    "mobId": 6130101,
    "mobName": "Mushmom",
    "itemId": 2040504,
    "itemName": "Scroll for Overall Armor for Defense 60%",
    "chance": 0.003,
    "minQty": 1,
    "maxQty": 1,
    "chineseItemName": "套服防禦卷軸60%",
    "chineseMobName": "蘑菇王"
  },
  {
    "mobId": 6130101,
    "mobName": "Mushmom",
    "itemId": 2040601,
    "itemName": "Scroll for Bottomwear for Defense 60%",
    "chance": 0.003,
    "minQty": 1,
    "maxQty": 1,
    "chineseItemName": "褲裙防禦卷軸60%",
    "chineseMobName": "蘑菇王"
  },
  {
    "mobId": 6130101,
    "mobName": "Mushmom",
    "itemId": 2040618,
    "itemName": "Scroll for Bottomwear for Mobility 60%",
    "chance": 0.003,
    "minQty": 1,
    "maxQty": 1,
    "chineseItemName": "褲裙跳躍卷軸60%",
    "chineseMobName": "蘑菇王"
  },
  {
    "mobId": 6130101,
    "mobName": "Mushmom",
    "itemId": 2040619,
    "itemName": "Scroll for Bottomwear for Mobility 10%",
    "chance": 0.003,
    "minQty": 1,
    "maxQty": 1,
    "chineseItemName": "褲裙跳躍卷軸10%",
    "chineseMobName": "蘑菇王"
  },
  {
    "mobId": 6130101,
    "mobName": "Mushmom",
    "itemId": 2040701,
    "itemName": "Scroll for Shoes for Avoidability 60%",
    "chance": 0.003,
    "minQty": 1,
    "maxQty": 1,
    "chineseItemName": "鞋子敏捷卷軸60%",
    "chineseMobName": "蘑菇王"
  },
  {
    "mobId": 6130101,
    "mobName": "Mushmom",
    "itemId": 2040704,
    "itemName": "Scroll for Shoes for Jump 60%",
    "chance": 0.003,
    "minQty": 1,
    "maxQty": 1,
    "chineseItemName": "鞋子跳躍卷軸60%",
    "chineseMobName": "蘑菇王"
  },
  {
    "mobId": 6130101,
    "mobName": "Mushmom",
    "itemId": 2040707,
    "itemName": "Scroll for Shoes for Mobility 60%",
    "chance": 0.003,
    "minQty": 1,
    "maxQty": 1,
    "chineseItemName": "鞋子速度卷軸60%",
    "chineseMobName": "蘑菇王"
  },
  {
    "mobId": 6130101,
    "mobName": "Mushmom",
    "itemId": 2040801,
    "itemName": "Scroll for Gloves for Accuracy 60%",
    "chance": 0.003,
    "minQty": 1,
    "maxQty": 1,
    "chineseItemName": "手套敏捷卷軸60%",
    "chineseMobName": "蘑菇王"
  },
  {
    "mobId": 6130101,
    "mobName": "Mushmom",
    "itemId": 2040804,
    "itemName": "Scroll for Gloves for ATT 60%",
    "chance": 0.003,
    "minQty": 1,
    "maxQty": 1,
    "chineseItemName": "手套攻擊卷軸60%",
    "chineseMobName": "蘑菇王"
  },
  {
    "mobId": 6130101,
    "mobName": "Mushmom",
    "itemId": 2040901,
    "itemName": "Scroll for Shield for Defense 60%",
    "chance": 0.003,
    "minQty": 1,
    "maxQty": 1,
    "chineseItemName": "盾牌防禦卷軸60%",
    "chineseMobName": "蘑菇王"
  },
  {
    "mobId": 6130101,
    "mobName": "Mushmom",
    "itemId": 2041004,
    "itemName": "Scroll for Cape for Defense 60%",
    "chance": 0.003,
    "minQty": 1,
    "maxQty": 1,
    "chineseItemName": "披風防禦卷軸60%",
    "chineseMobName": "蘑菇王"
  },
  {
    "mobId": 6130101,
    "mobName": "Mushmom",
    "itemId": 2043212,
    "itemName": "Scroll for One-Handed BW for Accuracy 60%",
    "chance": 0.003,
    "minQty": 1,
    "maxQty": 1,
    "chineseItemName": "單手棍命中卷軸60%",
    "chineseMobName": "蘑菇王"
  },
  {
    "mobId": 6130101,
    "mobName": "Mushmom",
    "itemId": 4000040,
    "itemName": "Mushmom Spore",
    "chance": 0.6,
    "minQty": 1,
    "maxQty": 1,
    "chineseItemName": "蘑菇王芽孢",
    "chineseMobName": "蘑菇王"
  }
]