[
  {
    "mobId": 9300659,
    "mobName": "Chunky Snail",
    "chineseMobName": "矮胖蝸牛",
    "itemId": 0,
    "itemName": "Meso",
    "chineseItemName": "楓幣",
    "chance": 0.4,
    "minQty": 28,
    "maxQty": 42
  },
  {
    "mobId": 9300659,
    "mobName": "Chunky Snail",
    "chineseMobName": "矮胖蝸牛",
    "itemId": 1002082,
    "itemName": "Yellow Bandana",
    "chineseItemName": "黃頭巾",
    "chance": 0.01,
    "minQty": 1,
    "maxQty": 1
  },
  {
    "mobId": 9300659,
    "mobName": "Chunky Snail",
    "chineseMobName": "矮胖蝸牛",
    "itemId": 1072043,
    "itemName": "Smelly Gomushin",
    "chineseItemName": "灰色膠鞋",
    "chance": 0.007,
    "minQty": 1,
    "maxQty": 1
  },
  {
    "mobId": 9300659,
    "mobName": "Chunky Snail",
    "chineseMobName": "矮胖蝸牛",
    "itemId": 1082150,
    "itemName": "Grey Work Gloves",
    "chineseItemName": "灰色工地手套",
    "chance": 0.007,
    "minQty": 1,
    "maxQty": 1
  },
  {
    "mobId": 9300659,
    "mobName": "Chunky Snail",
    "chineseMobName": "矮胖蝸牛",
    "itemId": 1092008,
    "itemName": "Pan Lid",
    "chineseItemName": "鍋蓋",
    "chance": 0.007,
    "minQty": 1,
    "maxQty": 1
  },
  {
    "mobId": 9300659,
    "mobName": "Chunky Snail",
    "chineseMobName": "矮胖蝸牛",
    "itemId": 1302007,
    "itemName": "Long Sword",
    "chineseItemName": "大劍",
    "chance": 0.007,
    "minQty": 1,
    "maxQty": 1
  },
  {
    "mobId": 9300659,
    "mobName": "Chunky Snail",
    "chineseMobName": "矮胖蝸牛",
    "itemId": 2010000,
    "itemName": "Apple",
    "chineseItemName": "蘋果",
    "chance": 0.02,
    "minQty": 1,
    "maxQty": 1
  },
  {
    "mobId": 9300659,
    "mobName": "Chunky Snail",
    "chineseMobName": "矮胖蝸牛",
    "itemId": 2010009,
    "itemName": "Green Apple",
    "chineseItemName": "青蘋果",
    "chance": 0.02,
    "minQty": 1,
    "maxQty": 1
  },
  {
    "mobId": 9300659,
    "mobName": "Chunky Snail",
    "chineseMobName": "矮胖蝸牛",
    "itemId": 4010006,
    "itemName": "Gold Ore",
    "chineseItemName": "黃金母礦",
    "chance": 0.009,
    "minQty": 1,
    "maxQty": 1
  }
]