{
  "id": 1040098,
  "description": {
    "id": 1040098,
    "name": "Light Scorpio",
    "description": "",
    "chineseItemName": "白飛影之服"
  },
  "metaInfo": {
    "only": false,
    "cash": false,
    "reqLevel": 60,
    "price": 90000,
    "reqSTR": 0,
    "reqDEX": 100,
    "reqINT": 0,
    "reqLUK": 170,
    "reqJob": 8,
    "reqLevelEquip": 60,
    "tuc": 7,
    "incDEX": 4,
    "incLUK": 1,
    "incPDD": 50
  },
  "typeInfo": {
    "overallCategory": "Equip",
    "category": "Armor",
    "subCategory": "Top"
  },
  "randomStats": {
    "incDEX": {
      "base": 4,
      "min": 1,
      "max": 7
    },
    "incLUK": {
      "base": 1,
      "min": 0,
      "max": 4
    },
    "incPDD": {
      "base": 50,
      "min": 20,
      "max": 80
    }
  },
  "isGachapon": true
}