{
  "id": 1060097,
  "description": {
    "id": 1060097,
    "name": "Green Pirate Pants",
    "description": "",
    "chineseItemName": "綠隱者之褲"
  },
  "metaInfo": {
    "only": false,
    "cash": false,
    "reqLevel": 80,
    "price": 120000,
    "reqSTR": 0,
    "reqDEX": 120,
    "reqINT": 0,
    "reqLUK": 220,
    "reqJob": 8,
    "reqLevelEquip": 80,
    "tuc": 7,
    "incDEX": 3,
    "incLUK": 1,
    "incPDD": 51
  },
  "typeInfo": {
    "overallCategory": "Equip",
    "category": "Armor",
    "subCategory": "Bottom"
  },
  "randomStats": {
    "incDEX": {
      "base": 3,
      "min": 0,
      "max": 7
    },
    "incLUK": {
      "base": 1,
      "min": 0,
      "max": 5
    },
    "incPDD": {
      "base": 51,
      "min": 11,
      "max": 91
    }
  },
  "isGachapon": true
}