{
  "id": 1072104,
  "description": {
    "id": 1072104,
    "name": "Red White-Lined Boots",
    "description": "",
    "chineseItemName": "紅楊柳鞋"
  },
  "metaInfo": {
    "only": false,
    "cash": false,
    "reqLevel": 35,
    "price": 20000,
    "reqSTR": 0,
    "reqDEX": 70,
    "reqINT": 0,
    "reqLUK": 95,
    "reqJob": 8,
    "reqLevelEquip": 35,
    "tuc": 5,
    "incLUK": 2,
    "incPDD": 19
  },
  "typeInfo": {
    "overallCategory": "Equip",
    "category": "Armor",
    "subCategory": "Shoes"
  },
  "randomStats": {
    "incLUK": {
      "base": 2,
      "min": 0,
      "max": 6
    },
    "incPDD": {
      "base": 19,
      "min": 1,
      "max": 37
    }
  },
  "isGachapon": true
}