{
  "id": 1082002,
  "description": {
    "id": 1082002,
    "name": "Work Gloves",
    "description": "",
    "chineseItemName": "工地手套"
  },
  "metaInfo": {
    "only": false,
    "cash": false,
    "reqLevel": 10,
    "price": 2000,
    "reqSTR": 0,
    "reqDEX": 0,
    "reqINT": 0,
    "reqLUK": 0,
    "reqJob": 0,
    "reqLevelEquip": 10,
    "tuc": 5,
    "incPDD": 2
  },
  "typeInfo": {
    "overallCategory": "Equip",
    "category": "Armor",
    "subCategory": "Glove"
  },
  "randomStats": {
    "incPDD": {
      "base": 2,
      "min": 0,
      "max": 7
    }
  }
}