{
  "id": 1102033,
  "description": {
    "id": 1102033,
    "name": "Red Giles Cape",
    "description": "",
    "chineseItemName": "紅龍紋披風"
  },
  "metaInfo": {
    "only": false,
    "cash": false,
    "reqLevel": 85,
    "price": 270000,
    "reqSTR": 0,
    "reqDEX": 0,
    "reqINT": 0,
    "reqLUK": 0,
    "reqJob": 0,
    "reqLevelEquip": 85,
    "tuc": 5,
    "incPDD": 31,
    "incMDD": 36
  },
  "typeInfo": {
    "overallCategory": "Equip",
    "category": "Armor",
    "subCategory": "Cape"
  },
  "randomStats": {
    "incPDD": {
      "base": 31,
      "min": 0,
      "max": 74
    },
    "incMDD": {
      "base": 36,
      "min": 0,
      "max": 79
    }
  },
  "isGachapon": true
}