{
  "mobId": 3000005,
  "mobName": "Brown Teddy",
  "chineseMobName": "褐色發條熊",
  "isBoss": false,
  "inGame": true,
  "drops": [
    {
      "itemId": 4000106,
      "itemName": "Teddy's Cotton",
      "chineseItemName": "玩具熊的棉花團",
      "chance": 60,
      "displayChance": "60.0%",
      "minQty": 1,
      "maxQty": 1,
      "questId": 0,
      "enabled": true
    },
    {
      "itemId": 0,
      "itemName": "Meso",
      "chineseItemName": "楓幣",
      "chance": 40,
      "displayChance": "40.0%",
      "minQty": 81,
      "maxQty": 119,
      "questId": 0,
      "enabled": true
    },
    {
      "itemId": 2000002,
      "itemName": "White Potion",
      "chineseItemName": "白色藥水",
      "chance": 2,
      "displayChance": "2.0%",
      "minQty": 1,
      "maxQty": 1,
      "questId": 0,
      "enabled": true
    },
    {
      "itemId": 2000003,
      "itemName": "Blue Potion",
      "chineseItemName": "藍色藥水",
      "chance": 2,
      "displayChance": "2.0%",
      "minQty": 1,
      "maxQty": 1,
      "questId": 0,
      "enabled": true
    },
    {
      "itemId": 4004001,
      "itemName": "Wisdom Crystal Ore",
      "chineseItemName": "智慧母礦",
      "chance": 1,
      "displayChance": "1.0%",
      "minQty": 1,
      "maxQty": 1,
      "questId": 0,
      "enabled": true
    },
    {
      "itemId": 4010001,
      "itemName": "Steel Ore",
      "chineseItemName": "鋼鐵母礦",
      "chance": 0.9,
      "displayChance": "0.90%",
      "minQty": 1,
      "maxQty": 1,
      "questId": 0,
      "enabled": true
    },
    {
      "itemId": 4020000,
      "itemName": "Garnet Ore",
      "chineseItemName": "石榴石母礦",
      "chance": 0.9,
      "displayChance": "0.90%",
      "minQty": 1,
      "maxQty": 1,
      "questId": 0,
      "enabled": true
    },
    {
      "itemId": 1002013,
      "itemName": "Golden Pride",
      "chineseItemName": "孫悟空頭箍",
      "chance": 0.1287,
      "displayChance": "0.13%",
      "minQty": 1,
      "maxQty": 1,
      "questId": 0,
      "enabled": true
    },
    {
      "itemId": 1040058,
      "itemName": "Dark Silver Stealer",
      "chineseItemName": "黑銀寂靜之服",
      "chance": 0.08,
      "displayChance": "0.080%",
      "minQty": 1,
      "maxQty": 1,
      "questId": 0,
      "enabled": true
    },
    {
      "itemId": 1041058,
      "itemName": "Blood Sneak",
      "chineseItemName": "紅敏捷之服",
      "chance": 0.08,
      "displayChance": "0.080%",
      "minQty": 1,
      "maxQty": 1,
      "questId": 0,
      "enabled": true
    },
    {
      "itemId": 1060044,
      "itemName": "Dark Silver Stealer Pants",
      "chineseItemName": "黑銀寂靜之褲",
      "chance": 0.08,
      "displayChance": "0.080%",
      "minQty": 1,
      "maxQty": 1,
      "questId": 0,
      "enabled": true
    },
    {
      "itemId": 1061054,
      "itemName": "Blood Sneak Pants",
      "chineseItemName": "紅敏捷褲",
      "chance": 0.08,
      "displayChance": "0.080%",
      "minQty": 1,
      "maxQty": 1,
      "questId": 0,
      "enabled": true
    },
    {
      "itemId": 1072101,
      "itemName": "Blue Silky Boots",
      "chineseItemName": "藍錦絲鞋",
      "chance": 0.08,
      "displayChance": "0.080%",
      "minQty": 1,
      "maxQty": 1,
      "questId": 0,
      "enabled": true
    },
    {
      "itemId": 1050030,
      "itemName": "Blue Chaos Robe",
      "chineseItemName": "藍魔力長袍",
      "chance": 0.07,
      "displayChance": "0.070%",
      "minQty": 1,
      "maxQty": 1,
      "questId": 0,
      "enabled": true
    },
    {
      "itemId": 1052107,
      "itemName": "Brown Pollard",
      "chineseItemName": "褐色無袖服",
      "chance": 0.07,
      "displayChance": "0.070%",
      "minQty": 1,
      "maxQty": 1,
      "questId": 0,
      "enabled": true
    },
    {
      "itemId": 1082007,
      "itemName": "Bronze Missel",
      "chineseItemName": "青銅機器手套",
      "chance": 0.07,
      "displayChance": "0.070%",
      "minQty": 1,
      "maxQty": 1,
      "questId": 0,
      "enabled": true
    },
    {
      "itemId": 1082046,
      "itemName": "Steel Arbion",
      "chineseItemName": "鋼鐵追擊手套",
      "chance": 0.07,
      "displayChance": "0.070%",
      "minQty": 1,
      "maxQty": 1,
      "questId": 0,
      "enabled": true
    },
    {
      "itemId": 1322014,
      "itemName": "War Hammer",
      "chineseItemName": "大戰鬥錘",
      "chance": 0.07,
      "displayChance": "0.070%",
      "minQty": 1,
      "maxQty": 1,
      "questId": 0,
      "enabled": true
    },
    {
      "itemId": 1472014,
      "itemName": "Steel Avarice",
      "chineseItemName": "鋼鐵護腕",
      "chance": 0.07,
      "displayChance": "0.070%",
      "minQty": 1,
      "maxQty": 1,
      "questId": 0,
      "enabled": true
    },
    {
      "itemId": 1462000,
      "itemName": "Mountain Crossbow",
      "chineseItemName": "山羊弩",
      "chance": 0.05,
      "displayChance": "0.050%",
      "minQty": 1,
      "maxQty": 1,
      "questId": 0,
      "enabled": true
    },
    {
      "itemId": 2040701,
      "itemName": "Scroll for Shoes for Avoidability 60%",
      "chineseItemName": "鞋子迴避卷軸60%",
      "chance": 0.03,
      "displayChance": "0.030%",
      "minQty": 1,
      "maxQty": 1,
      "questId": 0,
      "enabled": true
    }
  ],
  "totalDrops": 21
}