{
  "mobId": 3210100,
  "mobName": "Fire Boar",
  "chineseMobName": "火肥肥",
  "isBoss": false,
  "inGame": true,
  "drops": [
    {
      "itemId": 4000024,
      "itemName": "Fire Boar's Tooth",
      "chineseItemName": "火肥肥尖牙",
      "chance": 60,
      "displayChance": "60.0%",
      "minQty": 1,
      "maxQty": 1,
      "questId": 0,
      "enabled": true
    },
    {
      "itemId": 0,
      "itemName": "Meso",
      "chineseItemName": "楓幣",
      "chance": 40,
      "displayChance": "40.0%",
      "minQty": 76,
      "maxQty": 114,
      "questId": 0,
      "enabled": true
    },
    {
      "itemId": 4000021,
      "itemName": "Leather",
      "chineseItemName": "動物皮",
      "chance": 5,
      "displayChance": "5.0%",
      "minQty": 1,
      "maxQty": 1,
      "questId": 0,
      "enabled": true
    },
    {
      "itemId": 2000001,
      "itemName": "Orange Potion",
      "chineseItemName": "橘色藥水",
      "chance": 2,
      "displayChance": "2.0%",
      "minQty": 1,
      "maxQty": 1,
      "questId": 0,
      "enabled": true
    },
    {
      "itemId": 2000002,
      "itemName": "White Potion",
      "chineseItemName": "白色藥水",
      "chance": 2,
      "displayChance": "2.0%",
      "minQty": 1,
      "maxQty": 1,
      "questId": 0,
      "enabled": true
    },
    {
      "itemId": 2000003,
      "itemName": "Blue Potion",
      "chineseItemName": "藍色藥水",
      "chance": 2,
      "displayChance": "2.0%",
      "minQty": 1,
      "maxQty": 1,
      "questId": 0,
      "enabled": true
    },
    {
      "itemId": 4010001,
      "itemName": "Steel Ore",
      "chineseItemName": "鋼鐵母礦",
      "chance": 0.9,
      "displayChance": "0.90%",
      "minQty": 1,
      "maxQty": 1,
      "questId": 0,
      "enabled": true
    },
    {
      "itemId": 4010002,
      "itemName": "Mithril Ore",
      "chineseItemName": "鋰礦石母礦",
      "chance": 0.9,
      "displayChance": "0.90%",
      "minQty": 1,
      "maxQty": 1,
      "questId": 0,
      "enabled": true
    },
    {
      "itemId": 4020000,
      "itemName": "Garnet Ore",
      "chineseItemName": "石榴石母礦",
      "chance": 0.9,
      "displayChance": "0.90%",
      "minQty": 1,
      "maxQty": 1,
      "questId": 0,
      "enabled": true
    },
    {
      "itemId": 4020007,
      "itemName": "Diamond Ore",
      "chineseItemName": "鑽石母礦",
      "chance": 0.9,
      "displayChance": "0.90%",
      "minQty": 1,
      "maxQty": 1,
      "questId": 0,
      "enabled": true
    },
    {
      "itemId": 4006001,
      "itemName": "The Summoning Rock",
      "chineseItemName": "召喚石",
      "chance": 0.7,
      "displayChance": "0.70%",
      "minQty": 1,
      "maxQty": 1,
      "questId": 0,
      "enabled": true
    },
    {
      "itemId": 1002141,
      "itemName": "Red Matty",
      "chineseItemName": "紅星魔法帽",
      "chance": 0.1287,
      "displayChance": "0.13%",
      "minQty": 1,
      "maxQty": 1,
      "questId": 0,
      "enabled": true
    },
    {
      "itemId": 1002178,
      "itemName": "Green Burgler",
      "chineseItemName": "綠防風帽",
      "chance": 0.1287,
      "displayChance": "0.13%",
      "minQty": 1,
      "maxQty": 1,
      "questId": 0,
      "enabled": true
    },
    {
      "itemId": 1082044,
      "itemName": "Gold Sylvia",
      "chineseItemName": "黃金暴風手套",
      "chance": 0.1,
      "displayChance": "0.10%",
      "minQty": 1,
      "maxQty": 1,
      "questId": 0,
      "enabled": true
    },
    {
      "itemId": 1082052,
      "itemName": "Blue Lutia",
      "chineseItemName": "藍守護手套",
      "chance": 0.1,
      "displayChance": "0.10%",
      "minQty": 1,
      "maxQty": 1,
      "questId": 0,
      "enabled": true
    },
    {
      "itemId": 1040026,
      "itemName": "Green Hwarang Shirt",
      "chineseItemName": "綠龍服",
      "chance": 0.08,
      "displayChance": "0.080%",
      "minQty": 1,
      "maxQty": 1,
      "questId": 0,
      "enabled": true
    },
    {
      "itemId": 1060019,
      "itemName": "Brown Martial Arts Pants",
      "chineseItemName": "黃武褲",
      "chance": 0.08,
      "displayChance": "0.080%",
      "minQty": 1,
      "maxQty": 1,
      "questId": 0,
      "enabled": true
    },
    {
      "itemId": 1072079,
      "itemName": "Red Hunter Boots",
      "chineseItemName": "紅打獵鞋",
      "chance": 0.08,
      "displayChance": "0.080%",
      "minQty": 1,
      "maxQty": 1,
      "questId": 0,
      "enabled": true
    },
    {
      "itemId": 1072091,
      "itemName": "Black Salt Shoes",
      "chineseItemName": "黑守護鞋",
      "chance": 0.08,
      "displayChance": "0.080%",
      "minQty": 1,
      "maxQty": 1,
      "questId": 0,
      "enabled": true
    },
    {
      "itemId": 1072103,
      "itemName": "Red Silky Boots",
      "chineseItemName": "紅錦絲鞋",
      "chance": 0.08,
      "displayChance": "0.080%",
      "minQty": 1,
      "maxQty": 1,
      "questId": 0,
      "enabled": true
    },
    {
      "itemId": 1052107,
      "itemName": "Brown Pollard",
      "chineseItemName": "褐色無袖服",
      "chance": 0.07,
      "displayChance": "0.070%",
      "minQty": 1,
      "maxQty": 1,
      "questId": 0,
      "enabled": true
    },
    {
      "itemId": 1372003,
      "itemName": "Mithril Wand",
      "chineseItemName": "鋰礦短杖",
      "chance": 0.07,
      "displayChance": "0.070%",
      "minQty": 1,
      "maxQty": 1,
      "questId": 0,
      "enabled": true
    },
    {
      "itemId": 1372012,
      "itemName": "Crystal Wand",
      "chineseItemName": "水晶短杖",
      "chance": 0.07,
      "displayChance": "0.070%",
      "minQty": 1,
      "maxQty": 1,
      "questId": 0,
      "enabled": true
    },
    {
      "itemId": 1203001,
      "itemName": "Wolbi Throwing-Stars",
      "chineseItemName": "迴旋鏢",
      "chance": 0.05,
      "displayChance": "0.050%",
      "minQty": 1,
      "maxQty": 1,
      "questId": 0,
      "enabled": true
    },
    {
      "itemId": 1332020,
      "itemName": "Korean Fan",
      "chineseItemName": "太極扇",
      "chance": 0.05,
      "displayChance": "0.050%",
      "minQty": 1,
      "maxQty": 1,
      "questId": 0,
      "enabled": true
    },
    {
      "itemId": 1452005,
      "itemName": "Ryden",
      "chineseItemName": "雷電",
      "chance": 0.05,
      "displayChance": "0.050%",
      "minQty": 1,
      "maxQty": 1,
      "questId": 0,
      "enabled": true
    },
    {
      "itemId": 1462005,
      "itemName": "Heckler",
      "chineseItemName": "雙弦弩",
      "chance": 0.05,
      "displayChance": "0.050%",
      "minQty": 1,
      "maxQty": 1,
      "questId": 0,
      "enabled": true
    },
    {
      "itemId": 1472012,
      "itemName": "Silver Guardian",
      "chineseItemName": "銀守護拳套",
      "chance": 0.05,
      "displayChance": "0.050%",
      "minQty": 1,
      "maxQty": 1,
      "questId": 0,
      "enabled": true
    },
    {
      "itemId": 1203006,
      "itemName": "Kumbi Throwing-Stars",
      "chineseItemName": "雪花鏢",
      "chance": 0.04,
      "displayChance": "0.040%",
      "minQty": 1,
      "maxQty": 1,
      "questId": 0,
      "enabled": true
    }
  ],
  "totalDrops": 29
}