{
  "mobId": 8645263,
  "mobName": "Turbo Robo",
  "chineseMobName": null,
  "isBoss": false,
  "inGame": true,
  "totalDrops": 30,
  "drops": [
    {
      "itemId": 1202001,
      "itemName": "Split Bullet",
      "chineseItemName": null,
      "chance": 0.05,
      "displayChance": "0.050%",
      "minQty": 1,
      "maxQty": 1,
      "questId": 0,
      "enabled": true
    },
    {
      "itemId": 4010001,
      "itemName": "Steel Ore",
      "chineseItemName": null,
      "chance": 0.03,
      "displayChance": "0.030%",
      "minQty": 1,
      "maxQty": 1,
      "questId": 0,
      "enabled": true
    },
    {
      "itemId": 4020002,
      "itemName": "AquaMarine Ore",
      "chineseItemName": null,
      "chance": 0.03,
      "displayChance": "0.030%",
      "minQty": 1,
      "maxQty": 1,
      "questId": 0,
      "enabled": true
    },
    {
      "itemId": 0,
      "itemName": "Meso",
      "chineseItemName": null,
      "chance": 0,
      "displayChance": "0.000%",
      "minQty": 1,
      "maxQty": 141,
      "questId": 0,
      "enabled": true
    },
    {
      "itemId": 1002024,
      "itemName": "Emerald Dome",
      "chineseItemName": null,
      "chance": 0,
      "displayChance": "0.000%",
      "minQty": 1,
      "maxQty": 1,
      "questId": 0,
      "enabled": true
    },
    {
      "itemId": 1002628,
      "itemName": "Red Misty",
      "chineseItemName": null,
      "chance": 0,
      "displayChance": "0.000%",
      "minQty": 1,
      "maxQty": 1,
      "questId": 0,
      "enabled": true
    },
    {
      "itemId": 1032018,
      "itemName": "Pansy Earrings",
      "chineseItemName": null,
      "chance": 0,
      "displayChance": "0.000%",
      "minQty": 800,
      "maxQty": 1,
      "questId": 0,
      "enabled": true
    },
    {
      "itemId": 1052113,
      "itemName": "Red Barbay",
      "chineseItemName": null,
      "chance": 0,
      "displayChance": "0.000%",
      "minQty": 800,
      "maxQty": 1,
      "questId": 0,
      "enabled": true
    },
    {
      "itemId": 1060078,
      "itemName": "Umber Shouldermail Pants",
      "chineseItemName": null,
      "chance": 0,
      "displayChance": "0.000%",
      "minQty": 1,
      "maxQty": 1,
      "questId": 0,
      "enabled": true
    },
    {
      "itemId": 1072134,
      "itemName": "Orihalcon Hildon Boots",
      "chineseItemName": null,
      "chance": 0,
      "displayChance": "0.000%",
      "minQty": 1,
      "maxQty": 1,
      "questId": 0,
      "enabled": true
    },
    {
      "itemId": 1072285,
      "itemName": "Brown Lagger Slipper",
      "chineseItemName": null,
      "chance": 0,
      "displayChance": "0.000%",
      "minQty": 1,
      "maxQty": 1,
      "questId": 0,
      "enabled": true
    },
    {
      "itemId": 1072300,
      "itemName": "Brown Leather Krag",
      "chineseItemName": null,
      "chance": 0,
      "displayChance": "0.000%",
      "minQty": 1,
      "maxQty": 1,
      "questId": 0,
      "enabled": true
    },
    {
      "itemId": 1082050,
      "itemName": "Black Marker",
      "chineseItemName": null,
      "chance": 0,
      "displayChance": "0.000%",
      "minQty": 1,
      "maxQty": 1,
      "questId": 0,
      "enabled": true
    },
    {
      "itemId": 1082195,
      "itemName": "Brown Barbee",
      "chineseItemName": null,
      "chance": 0,
      "displayChance": "0.000%",
      "minQty": 1,
      "maxQty": 1,
      "questId": 0,
      "enabled": true
    },
    {
      "itemId": 1102003,
      "itemName": "White Napoleon",
      "chineseItemName": null,
      "chance": 0,
      "displayChance": "0.000%",
      "minQty": 1,
      "maxQty": 1,
      "questId": 0,
      "enabled": true
    },
    {
      "itemId": 1302016,
      "itemName": "Yellow Umbrella",
      "chineseItemName": null,
      "chance": 0,
      "displayChance": "0.000%",
      "minQty": 800,
      "maxQty": 1,
      "questId": 0,
      "enabled": true
    },
    {
      "itemId": 1322017,
      "itemName": "Knuckle Mace",
      "chineseItemName": null,
      "chance": 0,
      "displayChance": "0.000%",
      "minQty": 800,
      "maxQty": 1,
      "questId": 0,
      "enabled": true
    },
    {
      "itemId": 1332016,
      "itemName": "Sai",
      "chineseItemName": null,
      "chance": 0,
      "displayChance": "0.000%",
      "minQty": 287,
      "maxQty": 1,
      "questId": 0,
      "enabled": true
    },
    {
      "itemId": 1372012,
      "itemName": "Crystal Wand",
      "chineseItemName": null,
      "chance": 0,
      "displayChance": "0.000%",
      "minQty": 800,
      "maxQty": 1,
      "questId": 0,
      "enabled": true
    },
    {
      "itemId": 2000010,
      "itemName": "Blue Pill",
      "chineseItemName": null,
      "chance": 0,
      "displayChance": "0.000%",
      "minQty": 1,
      "maxQty": 1,
      "questId": 0,
      "enabled": true
    },
    {
      "itemId": 2040516,
      "itemName": "Scroll for Overall Armor for LUK 60%",
      "chineseItemName": null,
      "chance": 0,
      "displayChance": "0.000%",
      "minQty": 1,
      "maxQty": 1,
      "questId": 0,
      "enabled": true
    },
    {
      "itemId": 2040704,
      "itemName": "Scroll for Shoes for Jump 60%",
      "chineseItemName": null,
      "chance": 0,
      "displayChance": "0.000%",
      "minQty": 1,
      "maxQty": 1,
      "questId": 0,
      "enabled": true
    },
    {
      "itemId": 2044501,
      "itemName": "Scroll for Bow for ATT 60%",
      "chineseItemName": null,
      "chance": 0,
      "displayChance": "0.000%",
      "minQty": 1,
      "maxQty": 1,
      "questId": 0,
      "enabled": true
    },
    {
      "itemId": 2050004,
      "itemName": "All Cure Potion",
      "chineseItemName": null,
      "chance": 0,
      "displayChance": "0.000%",
      "minQty": 1,
      "maxQty": 1,
      "questId": 0,
      "enabled": true
    },
    {
      "itemId": 4000995,
      "itemName": "#N/A",
      "chineseItemName": null,
      "chance": 0,
      "displayChance": "0.000%",
      "minQty": 1,
      "maxQty": 1,
      "questId": 0,
      "enabled": true
    },
    {
      "itemId": 4004001,
      "itemName": "Wisdom Crystal Ore",
      "chineseItemName": null,
      "chance": 0,
      "displayChance": "0.000%",
      "minQty": 1,
      "maxQty": 1,
      "questId": 0,
      "enabled": true
    },
    {
      "itemId": 4006000,
      "itemName": "The Magic Rock",
      "chineseItemName": null,
      "chance": 0,
      "displayChance": "0.000%",
      "minQty": 1,
      "maxQty": 1,
      "questId": 0,
      "enabled": true
    },
    {
      "itemId": 4010000,
      "itemName": "Bronze Ore",
      "chineseItemName": null,
      "chance": 0,
      "displayChance": "0.000%",
      "minQty": 1,
      "maxQty": 1,
      "questId": 0,
      "enabled": true
    },
    {
      "itemId": 4130000,
      "itemName": "Gloves Production Stimulator",
      "chineseItemName": null,
      "chance": 0,
      "displayChance": "0.000%",
      "minQty": 1,
      "maxQty": 1,
      "questId": 0,
      "enabled": false
    },
    {
      "itemId": 4131008,
      "itemName": "Wand Production Manual",
      "chineseItemName": null,
      "chance": 0,
      "displayChance": "0.000%",
      "minQty": 1,
      "maxQty": 1,
      "questId": 0,
      "enabled": false
    }
  ]
}