{
  "itemId": 1072179,
  "itemName": "Dark Enigma Shoes",
  "chineseItemName": "黑密林之鞋",
  "totalMonsters": 2,
  "monsters": [
    {
      "mobId": 8143000,
      "mobName": "Grim Phantom Watch",
      "chineseMobName": "怨靈女巫",
      "isBoss": false,
      "inGame": true,
      "chance": 0.08,
      "displayChance": "0.080%",
      "minQty": 1,
      "maxQty": 1
    },
    {
      "mobId": 8160000,
      "mobName": "Gatekeeper",
      "chineseMobName": "通道守門人",
      "isBoss": false,
      "inGame": true,
      "chance": 0.08,
      "displayChance": "0.080%",
      "minQty": 1,
      "maxQty": 1
    }
  ]
}