{
  "itemId": 2040928,
  "itemName": "Scroll for Shield for ATT 100%",
  "chineseItemName": null,
  "totalMonsters": 7,
  "monsters": [
    {
      "mobId": 2220000,
      "mobName": "Mano",
      "chineseMobName": "紅寶王",
      "isBoss": false,
      "inGame": true,
      "chance": 0.3,
      "displayChance": "0.30%",
      "minQty": 1,
      "maxQty": 1
    },
    {
      "mobId": 5220002,
      "mobName": "Faust",
      "chineseMobName": "殭屍猴王",
      "isBoss": true,
      "inGame": true,
      "chance": 0.3,
      "displayChance": "0.30%",
      "minQty": 1,
      "maxQty": 1
    },
    {
      "mobId": 6230600,
      "mobName": "Ice Drake",
      "chineseMobName": "冰龍",
      "isBoss": false,
      "inGame": true,
      "chance": 0.03,
      "displayChance": "0.030%",
      "minQty": 1,
      "maxQty": 1
    },
    {
      "mobId": 6230602,
      "mobName": "Officer Skeleton",
      "chineseMobName": "骷髏士官",
      "isBoss": false,
      "inGame": true,
      "chance": 0.03,
      "displayChance": "0.030%",
      "minQty": 1,
      "maxQty": 1
    },
    {
      "mobId": 7130010,
      "mobName": "Death Teddy",
      "chineseMobName": "怨靈發條熊",
      "isBoss": false,
      "inGame": true,
      "chance": 0.03,
      "displayChance": "0.030%",
      "minQty": 1,
      "maxQty": 1
    },
    {
      "mobId": 9834151,
      "mobName": "Tauroshield",
      "chineseMobName": "盾牌牛魔王",
      "isBoss": false,
      "inGame": true,
      "chance": 0.03,
      "displayChance": "0.030%",
      "minQty": 1,
      "maxQty": 1
    },
    {
      "mobId": 5150000,
      "mobName": "Mixed Golem",
      "chineseMobName": "混種石巨人",
      "isBoss": false,
      "inGame": true,
      "chance": 0.015,
      "displayChance": "0.015%",
      "minQty": 1,
      "maxQty": 1
    }
  ]
}